dscribeai/__init__.py
dscribeai/client.py
dscribeai/exceptions/__init__.py
dscribeai/exceptions/dscribeai_exception.py
dscribeai/models/__init__.py
dscribeai/models/analyze_data.py
dscribeai/models/analyze_response.py
dscribeai/models/error_response.py
dscribeai/models/paragraph.py
dscribeai/models/post_metadata.py
dscribeai/models/query_result.py
dscribeai/models/sentence.py
dscribeai/models/transcription_data.py
dscribeai/models/transcription_response.py
dscribeai-0.0.3.dist-info/METADATA
dscribeai-0.0.3.dist-info/WHEEL
dscribeai-0.0.3.dist-info/top_level.txt
dscribeai-0.0.3.dist-info/RECORD
