Metadata-Version: 2.4
Name: dscribeai
Version: 0.0.3
Summary: dScribe AI is an API to extract transcriptions and visual summaries from social media videos like TikTok, YouTube, Instagram, and X.
Author-email: dScribe AI <jordan@dscribeai.com>
Project-URL: Homepage, https://dscribeai.com?utm_source=pypi
Requires-Python: >=3.10
Requires-Dist: requests
Requires-Dist: pydantic
